{
  "film": {
    "image": "http://image.tmdb.org/t/p/w185/gHyIHWdPkO7Sh06fjxcmT9q6HLm.jpg",
    "name": "Tremors 4: The Legend Begins"
  },
  "cast": [
    {
      "name": "Michael Gross",
      "image": "http://image.tmdb.org/t/p/w185/9L3NARCTB8DIhr0psXigWag6TSB.jpg"
    },
    {
      "name": "Sara Botsford",
      "image": "http://image.tmdb.org/t/p/w185/piRF7asMtnG4RAht4Ev0y24o0Oi.jpg"
    },
    {
      "name": "Billy Drago",
      "image": "http://image.tmdb.org/t/p/w185/5KAkTHIYc9L3CMWJvKEHCeYUcFm.jpg"
    },
    {
      "name": "Brent Roam",
      "image": "http://image.tmdb.org/t/p/w185/mnME0nwThDk8rkkn0GmcsfzMw93.jpg"
    },
    {
      "name": "August Schellenberg",
      "image": "http://image.tmdb.org/t/p/w185/ixtGJRyOQJLFjkMynNvZAp2ZE8.jpg"
    },
    {
      "name": "J.E. Freeman",
      "image": "http://image.tmdb.org/t/p/w185/lGqZh89pfgSNhIItjvn34jPO6HM.jpg"
    },
    {
      "name": "Ming Lo"
    },
    {
      "name": "Lydia Look"
    },
    {
      "name": "Lydia Look"
    },
    {
      "name": "Neil Kopit"
    },
    {
      "name": "Sean Moran"
    },
    {
      "name": "Matthew Seth Wilson"
    }
  ]
}
