{
  "film": {
    "image": "http://image.tmdb.org/t/p/w185/rOCuTiZ3L3Y01eWINP2C01WSszz.jpg",
    "name": "Resisting Enemy Interrogation"
  },
  "cast": [
    {
      "name": "Rand Brooks",
      "image": "http://image.tmdb.org/t/p/w185/vWqNcOULc8juvA5zjsIARIbpSzH.jpg"
    },
    {
      "name": "Louis Adlon"
    },
    {
      "name": "George Dolenz",
      "image": "http://image.tmdb.org/t/p/w185/7ZLpMDLocmgHBMsYLTWjWHhmoP3.jpg"
    },
    {
      "name": "Poldi Dur"
    },
    {
      "name": "Carl Esmond",
      "image": "http://image.tmdb.org/t/p/w185/oIIC1bduiFRn0F0pa8Kh8jPPHbH.jpg"
    },
    {
      "name": "Steven Geray",
      "image": "http://image.tmdb.org/t/p/w185/1x9IJlRZ1HpIQXCNTvSQKwQZmgX.jpg"
    },
    {
      "name": "Arthur Kennedy",
      "image": "http://image.tmdb.org/t/p/w185/jpJ5x4SXyIBSPbDS6LqGvaoJoPv.jpg"
    },
    {
      "name": "Sam Locke"
    },
    {
      "name": "Lloyd Nolan",
      "image": "http://image.tmdb.org/t/p/w185/gh6Gli1hfPXKEJuh4tTXBGXdyuT.jpg"
    },
    {
      "name": "George O'Hanlon",
      "image": "http://image.tmdb.org/t/p/w185/2hrNnR9yoCpbtVvJIqbY7xvV5CI.jpg"
    },
    {
      "name": "Don Porter",
      "image": "http://image.tmdb.org/t/p/w185/6ZICq6pp1CCyplymj3gMoa3ktvL.jpg"
    },
    {
      "name": "James Seay",
      "image": "http://image.tmdb.org/t/p/w185/rPnm4LLQs4GvVzXhAmcBAUK9aFh.jpg"
    },
    {
      "name": "Kent Smith",
      "image": "http://image.tmdb.org/t/p/w185/4M9WHAqGkgLA164sfapVIpNF7og.jpg"
    },
    {
      "name": "Mel Tormé",
      "image": "http://image.tmdb.org/t/p/w185/efXQ71wXEIXzU9OxBOqNdF612RD.jpg"
    },
    {
      "name": "Peter van Eyck",
      "image": "http://image.tmdb.org/t/p/w185/xXkWcMKcFSEiupgII0VMCt942Zz.jpg"
    },
    {
      "name": "Hans Heinrich von Twardowski"
    },
    {
      "name": "Max Wilk"
    }
  ]
}
