{
  "film": {
    "name": "Upheaval"
  },
  "cast": [
    {
      "name": "Frances McDormand",
      "image": "http://image.tmdb.org/t/p/w185/heJwM65BLMfJGcXuphhZiv9unTo.jpg"
    },
    {
      "name": "David Chandler"
    },
    {
      "name": "Sarah Adler ",
      "image": "http://image.tmdb.org/t/p/w185/adZG4AY4e55cV9bB3PDryotBnMf.jpg"
    },
    {
      "name": "Ethan Klaris"
    },
    {
      "name": "Delores Yvonne Mitchell"
    },
    {
      "name": "James Urbaniak",
      "image": "http://image.tmdb.org/t/p/w185/3vWulMbILVGliEraXzMpWrTb4m7.jpg"
    },
    {
      "name": "Patricia Dunnock"
    },
    {
      "name": "Scott Sowers"
    },
    {
      "name": "Lisa Benavides"
    },
    {
      "name": "Julie Anderson"
    },
    {
      "name": "Olivia Birkelund"
    },
    {
      "name": "Julia Gibson"
    },
    {
      "name": "Pia Joy Mileaf-Patel"
    }
  ]
}
