{
  "film": {
    "image": "http://image.tmdb.org/t/p/w185/l5FmAe8N0RQQnqriwqCpMuzBxLW.jpg",
    "name": "Lo mejor que le puede pasar a un cruasán"
  },
  "cast": [
    {
      "name": "Pablo Carbonell",
      "image": "http://image.tmdb.org/t/p/w185/pjERUOxCMcwWTAunJjz0BVq6ku.jpg"
    },
    {
      "name": "Pep Ferrer"
    },
    {
      "name": "Nathalie Seseña",
      "image": "http://image.tmdb.org/t/p/w185/ws225b7pKLnuA3JPfjvfez4NYt7.jpg"
    },
    {
      "name": "José Coronado",
      "image": "http://image.tmdb.org/t/p/w185/co7XjJSCr4kk4LkeIdqpmMaoOis.jpg"
    }
  ]
}
