{
  "film": {
    "image": "http://image.tmdb.org/t/p/w185/9gU5UFPAlcmsBnayC6pjIh98sBp.jpg",
    "name": "Stalled"
  },
  "cast": [
    {
      "name": "Dan Palmer"
    },
    {
      "name": "Antonia Bernath",
      "image": "http://image.tmdb.org/t/p/w185/r8DI6C9YsbgoGGTuJrWoSAvE7iO.jpg"
    },
    {
      "name": "Tamaryn Payne",
      "image": "http://image.tmdb.org/t/p/w185/jTSKXcnZwfRJQyi0bn10Z1BPFR8.jpg"
    },
    {
      "name": "Mark Holden"
    },
    {
      "name": "Giles Alderson",
      "image": "http://image.tmdb.org/t/p/w185/l9O8o27CSQWdzDwHJCtNmdkJJ4h.jpg"
    },
    {
      "name": "Victoria Broom",
      "image": "http://image.tmdb.org/t/p/w185/1SDwFNV3IsgURu96h0ShzVTbXhs.jpg"
    },
    {
      "name": "Marcus Kelly"
    },
    {
      "name": "Victoria Eldon"
    },
    {
      "name": "Chris R. Wright"
    },
    {
      "name": "Rick Edwards"
    },
    {
      "name": "Russell Biles"
    }
  ]
}
