{
  "film": {
    "image": "http://image.tmdb.org/t/p/w185/5ewRdBs1g9ggT6rgTJJcM5PaJlC.jpg",
    "name": "Viva Zapata!"
  },
  "cast": [
    {
      "name": "Marlon Brando",
      "image": "http://image.tmdb.org/t/p/w185/u9ftdTglXZPDzHdvlcPCLgzNwSD.jpg"
    },
    {
      "name": "Jean Peters",
      "image": "http://image.tmdb.org/t/p/w185/xsHWIDGloEZcn7H65iQ6BUGy8Ni.jpg"
    },
    {
      "name": "Anthony Quinn",
      "image": "http://image.tmdb.org/t/p/w185/9sKpm4KCoUbmMbR86fpqcgBCHrJ.jpg"
    },
    {
      "name": "Joseph Wiseman",
      "image": "http://image.tmdb.org/t/p/w185/3BigmJ5RUpS2uGCZyYxNL7mnbfW.jpg"
    },
    {
      "name": "Arnold Moss",
      "image": "http://image.tmdb.org/t/p/w185/dzYW3sJFzM15zHlhb3PeHRxPPkI.jpg"
    },
    {
      "name": "Alan Reed",
      "image": "http://image.tmdb.org/t/p/w185/8s1O9NJNM8kZQCmlvfYdFUiyODt.jpg"
    },
    {
      "name": "Margo",
      "image": "http://image.tmdb.org/t/p/w185/7C3uTeLp3McAtK6ybtTFEQtPlEP.jpg"
    },
    {
      "name": "Harold Gordon"
    },
    {
      "name": "Lou Gilbert"
    },
    {
      "name": "Frank Silvera",
      "image": "http://image.tmdb.org/t/p/w185/l6Jv1ZvKjvfvvehwDroOKR2d6pa.jpg"
    },
    {
      "name": "Joseph Granby"
    },
    {
      "name": "Fay Roope"
    },
    {
      "name": "Frank Dekova",
      "image": "http://image.tmdb.org/t/p/w185/73gXe4nNFYXVnS3wB1DIJkaoO82.jpg"
    }
  ]
}
