{
  "film": {
    "image": "http://image.tmdb.org/t/p/w185/8ftyaKktGWgwPReblM4pB1uqtlu.jpg",
    "name": "Fur: An Imaginary Portrait of Diane Arbus"
  },
  "cast": [
    {
      "name": "Nicole Kidman",
      "image": "http://image.tmdb.org/t/p/w185/i58Dlu3gGhcyfGuFyWtxrJy7E0x.jpg"
    },
    {
      "name": "Robert Downey Jr.",
      "image": "http://image.tmdb.org/t/p/w185/iDtxXJXmJGU7jYRjsvePNQblHV1.jpg"
    },
    {
      "name": "Ty Burrell",
      "image": "http://image.tmdb.org/t/p/w185/gfyWzHvrnomobxaAW8MfCNSAifI.jpg"
    },
    {
      "name": "Harris Yulin",
      "image": "http://image.tmdb.org/t/p/w185/MCW4IR3mEB6oeRbX9bfeHkZ3qm.jpg"
    },
    {
      "name": "Jane Alexander",
      "image": "http://image.tmdb.org/t/p/w185/sy39obbxX2gcZW02HGci3JGFW6M.jpg"
    },
    {
      "name": "Emmy Clarke",
      "image": "http://image.tmdb.org/t/p/w185/vrdy4KrhjFKO8yWZgocNZkx3arJ.jpg"
    },
    {
      "name": "Genevieve McCarthy"
    },
    {
      "name": "Boris McGiver",
      "image": "http://image.tmdb.org/t/p/w185/l3wlcpfnl5ethAPDIfP4sNeWADm.jpg"
    },
    {
      "name": "Marceline Hugot"
    },
    {
      "name": "Mary Duffy"
    },
    {
      "name": "Emily Bergl",
      "image": "http://image.tmdb.org/t/p/w185/g9qdvOV3xtjPa57gK6rqRhTbOz8.jpg"
    },
    {
      "name": "Gwendolyn Bucci"
    },
    {
      "name": "Christina Rouner"
    },
    {
      "name": "Matt Servitto",
      "image": "http://image.tmdb.org/t/p/w185/tnDuy2gKDFrr2czXSCuxTkCGFdP.jpg"
    },
    {
      "name": "Lynn-Marie Stetson"
    }
  ]
}
