{
  "film": {
    "image": "http://image.tmdb.org/t/p/w185/c0L2OBId4M18B1EG6Q19QFF6JZ8.jpg",
    "name": "Entre rojas"
  },
  "cast": [
    {
      "name": "Penélope Cruz",
      "image": "http://image.tmdb.org/t/p/w185/8gAt6RNH5UHT9TIgbrH9sRLtc2r.jpg"
    },
    {
      "name": "Cristina Marcos"
    },
    {
      "name": "María Pujalte"
    },
    {
      "name": "Ana Torrent",
      "image": "http://image.tmdb.org/t/p/w185/xIpRwiCl2xAp2R3i9jV10ZfW2kC.jpg"
    },
    {
      "name": "Pilar Bardem",
      "image": "http://image.tmdb.org/t/p/w185/aPtXpY9memp6SQvAVZpzBbysI9U.jpg"
    },
    {
      "name": "Carmelo Gómez",
      "image": "http://image.tmdb.org/t/p/w185/dCuhHjDh1hXMTi1GRhqPktq5c6p.jpg"
    },
    {
      "name": "Chusa Barbero"
    }
  ]
}
