{
  "film": {
    "image": "http://image.tmdb.org/t/p/w185/vzejYbGVfths0uMUPIwNwBHuNYw.jpg",
    "name": "The End of the Affair"
  },
  "cast": [
    {
      "name": "Ralph Fiennes",
      "image": "http://image.tmdb.org/t/p/w185/95C56hfbvSA1UNvD433EzXviyV5.jpg"
    },
    {
      "name": "Stephen Rea",
      "image": "http://image.tmdb.org/t/p/w185/taD1NngDbW8cyCuacAT3YaecSEG.jpg"
    },
    {
      "name": "Julianne Moore",
      "image": "http://image.tmdb.org/t/p/w185/5TP6PXUMfVlckGfDAmAk8ijVpLX.jpg"
    },
    {
      "name": "James Bolam"
    },
    {
      "name": "Ian Hart",
      "image": "http://image.tmdb.org/t/p/w185/tAsLBMEaRv3S7AefSQwd1JlO71H.jpg"
    },
    {
      "name": "Jason Isaacs",
      "image": "http://image.tmdb.org/t/p/w185/xUlka8zpREdB0xIAiolOSC1t4CB.jpg"
    },
    {
      "name": "Deborah Findlay"
    },
    {
      "name": "Sam Bould"
    }
  ]
}
