{
  "film": {
    "image": "http://image.tmdb.org/t/p/w185/iLnBMZcf1ZDzD97nwF17Flmq1OX.jpg",
    "name": "Santorini Blue"
  },
  "cast": [
    {
      "name": "Deirdre Lorenz"
    },
    {
      "name": "Matthew D. Panepinto"
    },
    {
      "name": "Richard Belzer",
      "image": "http://image.tmdb.org/t/p/w185/z31x0H4tEHs0IPtdSpwMF2Ya5Pa.jpg"
    },
    {
      "name": "Dann Florek",
      "image": "http://image.tmdb.org/t/p/w185/aWRFqpmLdFAoH9BiUE7RyxUKUsX.jpg"
    },
    {
      "name": "Ice-T",
      "image": "http://image.tmdb.org/t/p/w185/4k6Bj2HtKrSnf46RsWQaMG1jvns.jpg"
    },
    {
      "name": "Clark Johnson",
      "image": "http://image.tmdb.org/t/p/w185/iaXZQUpcz5h8za1s6e1x60Fs6aj.jpg"
    },
    {
      "name": "Taylor Negron",
      "image": "http://image.tmdb.org/t/p/w185/wk0bOBqw47cMntR7IJvlE9hE372.jpg"
    }
  ]
}
