{
  "film": {
    "name": "A Call to Remember"
  },
  "cast": [
    {
      "name": "Blythe Danner",
      "image": "http://image.tmdb.org/t/p/w185/aLDiUFLLWWcPMi7lpnb3QqUPGnd.jpg"
    },
    {
      "name": "Joe Mantegna",
      "image": "http://image.tmdb.org/t/p/w185/puf1FzUBaysTzPbCR67IWdippCn.jpg"
    },
    {
      "name": "David Lascher",
      "image": "http://image.tmdb.org/t/p/w185/4anRGougLdrX44bqUsPekPxDqx4.jpg"
    },
    {
      "name": "Kevin Zegers",
      "image": "http://image.tmdb.org/t/p/w185/aztFaCIPiv9Me2DjTtiT7Qnbtm0.jpg"
    },
    {
      "name": "Joe Spano",
      "image": "http://image.tmdb.org/t/p/w185/7n6nbIUkO1KJ91ryw7I9fqwTuGu.jpg"
    }
  ]
}
