{
  "film": {
    "image": "http://image.tmdb.org/t/p/w185/3VB0jaPI6eOmDvAdmoJtSMPeNUn.jpg",
    "name": "Girls in Prison"
  },
  "cast": [
    {
      "name": "Anne Heche",
      "image": "http://image.tmdb.org/t/p/w185/aXMySUgcAJ09dq0oD0qY1mcsr1c.jpg"
    },
    {
      "name": "Ione Skye",
      "image": "http://image.tmdb.org/t/p/w185/zRPIdTnEQO4FioH8wqr0lNQgNmg.jpg"
    },
    {
      "name": "Missy Crider"
    },
    {
      "name": "Nicolette Scorsese"
    },
    {
      "name": "Bahni Turpin"
    },
    {
      "name": "Jon Polito",
      "image": "http://image.tmdb.org/t/p/w185/3Ws9qCNzMBz16YqUyX6n262XuIl.jpg"
    },
    {
      "name": "Nestor Serrano",
      "image": "http://image.tmdb.org/t/p/w185/A3XSP0FLTFfUusJFBAy83w2yYzj.jpg"
    },
    {
      "name": "Miguel Sandoval",
      "image": "http://image.tmdb.org/t/p/w185/7pCh6a4JMtxyZ3hziQjfa6rdh93.jpg"
    },
    {
      "name": "Richmond Arquette",
      "image": "http://image.tmdb.org/t/p/w185/xW4bb2qsPYilO27ex4Xoy2Ik1Ai.jpg"
    },
    {
      "name": "Raymond O'Connor",
      "image": "http://image.tmdb.org/t/p/w185/bIC6drKtKjr4F2GXQwbBgJGh8y9.jpg"
    },
    {
      "name": "Tom Towles"
    },
    {
      "name": "William Boyett",
      "image": "http://image.tmdb.org/t/p/w185/bhVCfjezGU3zRe3c6od8bC1dOEC.jpg"
    },
    {
      "name": "Angie Rae McKinney"
    },
    {
      "name": "Diane McGee"
    },
    {
      "name": "Harvey Chao"
    },
    {
      "name": "Ralph Meyering Jr."
    },
    {
      "name": "Letitia Hicks"
    },
    {
      "name": "J. Patrick McCormack"
    },
    {
      "name": "William C. Clark"
    },
    {
      "name": "David Paul Needles"
    },
    {
      "name": "Tamara Clatterbuck",
      "image": "http://image.tmdb.org/t/p/w185/tDH8CQPqUJ54ralcDy8xJkxu1Fz.jpg"
    },
    {
      "name": "Martin Charles Warner"
    },
    {
      "name": "Richard Saxton"
    },
    {
      "name": "Rick Cicetti"
    }
  ]
}
