{
  "film": {
    "image": "http://image.tmdb.org/t/p/w185/18haTIVMnM4AhO9UW6xawkp1puY.jpg",
    "name": "Plaza Suite"
  },
  "cast": [
    {
      "name": "Walter Matthau",
      "image": "http://image.tmdb.org/t/p/w185/xJVkvprOnzP5Zdh5y63y8HHniDZ.jpg"
    },
    {
      "name": "Lee Grant",
      "image": "http://image.tmdb.org/t/p/w185/uTlYhUFxQBhpYvNVDNtnWadnK7f.jpg"
    },
    {
      "name": "Barbara Harris",
      "image": "http://image.tmdb.org/t/p/w185/j3c7qYmGUI3jQyEVBFA9F4RJWL6.jpg"
    },
    {
      "name": "Maureen Stapleton",
      "image": "http://image.tmdb.org/t/p/w185/7zazX6qycXK1CBXkNT1t9FCEEkk.jpg"
    },
    {
      "name": "Louise Sorel",
      "image": "http://image.tmdb.org/t/p/w185/ovg4HS2uaH5DSRayL5pR7sSGjk4.jpg"
    },
    {
      "name": "Dan Ferrone"
    }
  ]
}
