{
  "film": {
    "image": "http://image.tmdb.org/t/p/w185/7WILDjnJggB3bIioS3LRvtvmu1X.jpg",
    "name": "Cars 2"
  },
  "cast": [
    {
      "name": "Owen Wilson",
      "image": "http://image.tmdb.org/t/p/w185/j7OAiUKkcckSmixWL8FoacqQnx4.jpg"
    },
    {
      "name": "Michael Caine",
      "image": "http://image.tmdb.org/t/p/w185/nlIjMLp9zvvYM2eFm77UhI7s1nW.jpg"
    },
    {
      "name": "Emily Mortimer",
      "image": "http://image.tmdb.org/t/p/w185/jSw6VNNFXCc0cEAbGHafiWOWRKU.jpg"
    },
    {
      "name": "Michael Keaton",
      "image": "http://image.tmdb.org/t/p/w185/jSG7yQxSsGzz1TbDjq0811W5LK4.jpg"
    },
    {
      "name": "Jason Isaacs",
      "image": "http://image.tmdb.org/t/p/w185/xUlka8zpREdB0xIAiolOSC1t4CB.jpg"
    },
    {
      "name": "Bonnie Hunt",
      "image": "http://image.tmdb.org/t/p/w185/lwEvPd4SXprCLBnPzXUaH5pm33w.jpg"
    },
    {
      "name": "John Ratzenberger",
      "image": "http://image.tmdb.org/t/p/w185/xQ5UQMpxTNIiNoa3njt8WVMjvJd.jpg"
    },
    {
      "name": "Tony Shalhoub",
      "image": "http://image.tmdb.org/t/p/w185/jXzlVxS8u64XEZUoNPiuhGcQXDW.jpg"
    },
    {
      "name": "Larry the Cable Guy",
      "image": "http://image.tmdb.org/t/p/w185/9yGwJBveIvLidqJEQI4PRuKQhMr.jpg"
    },
    {
      "name": "Eddie Izzard",
      "image": "http://image.tmdb.org/t/p/w185/x5Fzw98kqTLcWhqisNbzNQsNnL7.jpg"
    },
    {
      "name": "John Turturro",
      "image": "http://image.tmdb.org/t/p/w185/yyvj3z2IC9AG1sv6kuk5d7oQFJs.jpg"
    },
    {
      "name": "Brent Musburger"
    },
    {
      "name": "Joe Mantegna",
      "image": "http://image.tmdb.org/t/p/w185/puf1FzUBaysTzPbCR67IWdippCn.jpg"
    },
    {
      "name": "Thomas Kretschmann",
      "image": "http://image.tmdb.org/t/p/w185/allahLWNWLQpeY46nUg1d6zSO7T.jpg"
    },
    {
      "name": "Darrell Waltrip"
    },
    {
      "name": "Franco Nero",
      "image": "http://image.tmdb.org/t/p/w185/f9ncJubHyIVngr7Itbbf9YA4Us7.jpg"
    },
    {
      "name": "David Hobbs"
    },
    {
      "name": "Patrick Walker"
    },
    {
      "name": "Jeff Garlin",
      "image": "http://image.tmdb.org/t/p/w185/exE7xhmaBnpAfbt4y0oqy2mc79M.jpg"
    },
    {
      "name": "Michel Michelis"
    },
    {
      "name": "Vanessa Redgrave",
      "image": "http://image.tmdb.org/t/p/w185/5yoWBiVPqrq0nn5WZRzqTwQQ3SF.jpg"
    },
    {
      "name": "Cheech Marin",
      "image": "http://image.tmdb.org/t/p/w185/5xzxA3l9MYLwQbJX8nxDImSafDG.jpg"
    },
    {
      "name": "Peter Jacobson",
      "image": "http://image.tmdb.org/t/p/w185/hSkwPVwOdcrhWoz9oS0KoUi8Q1I.jpg"
    }
  ]
}
