{
  "film": {
    "image": "http://image.tmdb.org/t/p/w185/solugFmCfz8k5Vo3cNJGafEGv7S.jpg",
    "name": "Handsome Harry"
  },
  "cast": [
    {
      "name": "Jamey Sheridan",
      "image": "http://image.tmdb.org/t/p/w185/xOhl3hP49XKTZuj8hzs2CdtMliT.jpg"
    },
    {
      "name": "Steve Buscemi",
      "image": "http://image.tmdb.org/t/p/w185/7sDzFRScCv85usSwPG01BTac7UY.jpg"
    },
    {
      "name": "Mariann Mayberry"
    },
    {
      "name": "Aidan Quinn",
      "image": "http://image.tmdb.org/t/p/w185/xNLXrmlFQbuh22KTVlJqOmNGIKC.jpg"
    }
  ]
}
