{
  "film": {
    "image": "http://image.tmdb.org/t/p/w185/dYrdxI5ty3SfMiep2GDvRyXEc4W.jpg",
    "name": "The Polar Express"
  },
  "cast": [
    {
      "name": "Tom Hanks",
      "image": "http://image.tmdb.org/t/p/w185/xxPMucou2wRDxLrud8i2D4dsywh.jpg"
    },
    {
      "name": "Michael Jeter",
      "image": "http://image.tmdb.org/t/p/w185/oJTjyq7RGOd1m49RvDpw12bQcvT.jpg"
    },
    {
      "name": "Eddie Deezen",
      "image": "http://image.tmdb.org/t/p/w185/ippZciGOX0PKn4QexVlcym4LZNS.jpg"
    },
    {
      "name": "Chris Coppola",
      "image": "http://image.tmdb.org/t/p/w185/A3vl2TSWtz5Fh1MTeCRs7vTz6Tk.jpg"
    },
    {
      "name": "Nona Gaye",
      "image": "http://image.tmdb.org/t/p/w185/tNwU5M0ylEuDtxqFLpNnNE7jFKb.jpg"
    },
    {
      "name": "Peter Scolari",
      "image": "http://image.tmdb.org/t/p/w185/tLSgD0c7i2rpIS5kNfTysy6Sz0P.jpg"
    },
    {
      "name": "Charles Fleischer",
      "image": "http://image.tmdb.org/t/p/w185/vlF5j4y3lEKO6wXJ1R98ixUmebx.jpg"
    },
    {
      "name": "Steven Tyler",
      "image": "http://image.tmdb.org/t/p/w185/tey8qIx6CmLm1AnCu4DBNUrPb9j.jpg"
    },
    {
      "name": "Leslie Zemeckis"
    },
    {
      "name": "Julene Renee",
      "image": "http://image.tmdb.org/t/p/w185/gONOL0vTflEd5yH1x3hcr2maFV5.jpg"
    },
    {
      "name": "Andy Pellick"
    }
  ]
}
