{
  "film": {
    "image": "http://image.tmdb.org/t/p/w185/Y6h7o9avrTqwYJg6IwJzhgHEdb.jpg",
    "name": "Kiss of Life"
  },
  "cast": [
    {
      "name": "Ingeborga Dapkunaite",
      "image": "http://image.tmdb.org/t/p/w185/6gtiuGdXyZgPY9ii0RphYEyeUpj.jpg"
    },
    {
      "name": "Peter Mullan",
      "image": "http://image.tmdb.org/t/p/w185/s6fVtjCu0HshEIbfLklz4e2OoWS.jpg"
    },
    {
      "name": "Millie Findlay"
    },
    {
      "name": "James Martin"
    },
    {
      "name": "Ivan Bijuk"
    },
    {
      "name": "Sonnell Dadral"
    },
    {
      "name": "Natalie Dew"
    }
  ]
}
