{
  "film": {
    "image": "http://image.tmdb.org/t/p/w185/dM2w364MScsjFf8pfMbaWUcWrR.jpg",
    "name": "Pulp Fiction"
  },
  "cast": [
    {
      "name": "Tim Roth",
      "image": "http://image.tmdb.org/t/p/w185/r4jtlboNqWPz2dOHafrPJE4Yd94.jpg"
    },
    {
      "name": "Amanda Plummer",
      "image": "http://image.tmdb.org/t/p/w185/4KXLjhrWpw7k5qcnSinoyZYHCL1.jpg"
    },
    {
      "name": "Laura Lovelace",
      "image": "http://image.tmdb.org/t/p/w185/hty1tWzaBThqc6AwuBlpanIeT4x.jpg"
    },
    {
      "name": "John Travolta",
      "image": "http://image.tmdb.org/t/p/w185/ns8uZHEHzV18ifqA9secv8c2Ard.jpg"
    },
    {
      "name": "Samuel L. Jackson",
      "image": "http://image.tmdb.org/t/p/w185/teciwVY9DIDNyCuYybKgrebF8bC.jpg"
    },
    {
      "name": "Phil LaMarr",
      "image": "http://image.tmdb.org/t/p/w185/nRCwM7qPDFa4Xwmz0N17pPrqpAA.jpg"
    },
    {
      "name": "Frank Whaley",
      "image": "http://image.tmdb.org/t/p/w185/ma1lgPwUHUlgdt9BIcIbEPjdx0h.jpg"
    },
    {
      "name": "Burr Steers",
      "image": "http://image.tmdb.org/t/p/w185/rWztkNxfPclLILEjAhaHaOHSWs3.jpg"
    },
    {
      "name": "Bruce Willis",
      "image": "http://image.tmdb.org/t/p/w185/kI1OluWhLJk3pnR19VjOfABpnTY.jpg"
    },
    {
      "name": "Ving Rhames",
      "image": "http://image.tmdb.org/t/p/w185/qfp236BgZ8S8sfFJvDTd3gjB3Ml.jpg"
    },
    {
      "name": "Paul Calderon",
      "image": "http://image.tmdb.org/t/p/w185/n3jppeBl8jhD7BHZhp4ExvfFdpD.jpg"
    },
    {
      "name": "Bronagh Gallagher",
      "image": "http://image.tmdb.org/t/p/w185/h44VuQ4yxA9ssITldXngDKSLoBQ.jpg"
    },
    {
      "name": "Rosanna Arquette",
      "image": "http://image.tmdb.org/t/p/w185/rQMQYQUF9QzD6oDfkP6tsjmyZhS.jpg"
    },
    {
      "name": "Eric Stoltz",
      "image": "http://image.tmdb.org/t/p/w185/fQF1k96Yo2fxL6w1oEskVB1NrfQ.jpg"
    },
    {
      "name": "Uma Thurman",
      "image": "http://image.tmdb.org/t/p/w185/jLnK2AA7GOmMaBbdv7Mb1yioJFv.jpg"
    },
    {
      "name": "Jerome Patrick Hoban"
    },
    {
      "name": "Michael Gilden"
    },
    {
      "name": "Gary Shorelle"
    },
    {
      "name": "Susan Griffiths"
    },
    {
      "name": "Eric Clark"
    },
    {
      "name": "Joseph Pilato",
      "image": "http://image.tmdb.org/t/p/w185/l5xtdrOmCgOrLiOs4HvyiLEmtNH.jpg"
    },
    {
      "name": "Brad Blumenthal"
    },
    {
      "name": "Steve Buscemi",
      "image": "http://image.tmdb.org/t/p/w185/7sDzFRScCv85usSwPG01BTac7UY.jpg"
    },
    {
      "name": "Lorelei Leslie"
    },
    {
      "name": "Emil Sitka"
    },
    {
      "name": "Brenda Hillhouse"
    },
    {
      "name": "Christopher Walken",
      "image": "http://image.tmdb.org/t/p/w185/t0gzpYe6FOWH1yKeRBOIpTKgFsB.jpg"
    },
    {
      "name": "Chandler Lindauer"
    },
    {
      "name": "Sy Sher"
    },
    {
      "name": "Robert Ruth"
    },
    {
      "name": "Rich Turner"
    },
    {
      "name": "Angela Jones",
      "image": "http://image.tmdb.org/t/p/w185/p7pNCt4uBTDk9kRkPU3BFfXfEPq.jpg"
    },
    {
      "name": "Don Blakely"
    },
    {
      "name": "Carl Allen"
    },
    {
      "name": "Maria de Medeiros",
      "image": "http://image.tmdb.org/t/p/w185/54cKyuWqzDbbyV2M5GfGBTIdUHQ.jpg"
    },
    {
      "name": "Karen Maruyama"
    },
    {
      "name": "Kathy Griffin",
      "image": "http://image.tmdb.org/t/p/w185/83vWmM5GgteuZ1UOU8QLxcKvYOm.jpg"
    },
    {
      "name": "Venessia Valentino"
    },
    {
      "name": "Linda Kaye"
    },
    {
      "name": "Duane Whitaker",
      "image": "http://image.tmdb.org/t/p/w185/cFSmuGjUNonH683dmvx0mZ2Uots.jpg"
    },
    {
      "name": "Peter Greene",
      "image": "http://image.tmdb.org/t/p/w185/wsTMORDoblpJfmdrssKOqP78aDl.jpg"
    },
    {
      "name": "Stephen Hibbert"
    },
    {
      "name": "Alexis Arquette",
      "image": "http://image.tmdb.org/t/p/w185/866b1XP6RVRXb9S3X6D7opfk7bR.jpg"
    },
    {
      "name": "Quentin Tarantino",
      "image": "http://image.tmdb.org/t/p/w185/6grjDWpEIPL5QdRbUZFxVEp5TCd.jpg"
    },
    {
      "name": "Harvey Keitel",
      "image": "http://image.tmdb.org/t/p/w185/oITNtWSDwA2hbuSuLdKXJZkXOSj.jpg"
    },
    {
      "name": "Julia Sweeney",
      "image": "http://image.tmdb.org/t/p/w185/hy7ZoNmr0h3AcrBkbnTLOXZnwRd.jpg"
    },
    {
      "name": "Lawrence Bender",
      "image": "http://image.tmdb.org/t/p/w185/5EzlP8qdCYQrhqEYB2MTmY74KFB.jpg"
    },
    {
      "name": "Cie Allman"
    },
    {
      "name": "Rene Beard"
    },
    {
      "name": "Lori Pizzo"
    },
    {
      "name": "Glendon Rich"
    },
    {
      "name": "Devan Richardson"
    },
    {
      "name": "Ani Sava"
    }
  ]
}
