{
  "film": {
    "image": "http://image.tmdb.org/t/p/w185/5PaX63v0EbDelKXXpHxzKBfU03m.jpg",
    "name": "The Holding"
  },
  "cast": [
    {
      "name": "David Bradley",
      "image": "http://image.tmdb.org/t/p/w185/r2vss74pTZzO4OMPYaB4hf5GMUH.jpg"
    },
    {
      "name": "Georgia Groome",
      "image": "http://image.tmdb.org/t/p/w185/nA1ZUpPGGGdwDhx3uOhE57DbTTy.jpg"
    },
    {
      "name": "Kierston Wareing",
      "image": "http://image.tmdb.org/t/p/w185/5o3sAfFNmG1r6ot40sHZB5toTBp.jpg"
    },
    {
      "name": "Terry Stone"
    },
    {
      "name": "Skye Lourie"
    },
    {
      "name": "Jake Curran"
    },
    {
      "name": "Mark Harris"
    },
    {
      "name": "David Hobbs"
    },
    {
      "name": "Eileen Davies"
    },
    {
      "name": "Christopher Brand"
    },
    {
      "name": "Maisie Lloyd"
    },
    {
      "name": "Gregory Oliver"
    },
    {
      "name": "Jarrod Cooke"
    },
    {
      "name": "Vincent Regan",
      "image": "http://image.tmdb.org/t/p/w185/tiyjPHwmX8dMMfx0F8HUpXyLHeY.jpg"
    }
  ]
}
