{
  "film": {
    "image": "http://image.tmdb.org/t/p/w185/uGexwiIvPC96owb2V8D5jvzfQ7D.jpg",
    "name": "Sharpe's Mission"
  },
  "cast": [
    {
      "name": "Sean Bean",
      "image": "http://image.tmdb.org/t/p/w185/arkVBI4myH8kvxFc7QIapy2DuT6.jpg"
    },
    {
      "name": "Daragh O'Malley",
      "image": "http://image.tmdb.org/t/p/w185/xHokRLUxBBKiDgzfyuJedC6nyKf.jpg"
    },
    {
      "name": "Abigail Cruttenden"
    },
    {
      "name": "James Laurenson"
    },
    {
      "name": "Hugh A. Robertson"
    },
    {
      "name": "Mark Strong",
      "image": "http://image.tmdb.org/t/p/w185/bFo6UXFjNLl18UMM2GmmpnL5feK.jpg"
    },
    {
      "name": "John Tams"
    }
  ]
}
