{
  "film": {
    "image": "http://image.tmdb.org/t/p/w185/3U7dKOuQzJ0vzTt4x2cBhMa4S7X.jpg",
    "name": "Charlotte Rampling: The Look"
  },
  "cast": [
    {
      "name": "Charlotte Rampling",
      "image": "http://image.tmdb.org/t/p/w185/2PitM5es6v6vUHohH6TLrChuLyY.jpg"
    },
    {
      "name": " Peter Lindbergh"
    },
    {
      "name": " Paul Auster"
    },
    {
      "name": " Barnaby Southcombe"
    },
    {
      "name": " Juergen Teller"
    },
    {
      "name": " Frederick Seidel"
    },
    {
      "name": "Franckie Diago"
    },
    {
      "name": " Anthony Palliser"
    },
    {
      "name": " Cynthia Fleury"
    },
    {
      "name": " Joy Fleury "
    }
  ]
}
