{
  "film": {
    "image": "http://image.tmdb.org/t/p/w185/mcjeBXKWcWyWyZq9oAyjbaCupEQ.jpg",
    "name": "Number One Fan"
  },
  "cast": [
    {
      "name": "Chad McQueen"
    },
    {
      "name": "Catherine Mary Stewart",
      "image": "http://image.tmdb.org/t/p/w185/2d3DEQluzVUPg9KJsn2vymIRlOW.jpg"
    },
    {
      "name": "Renee Griffin"
    },
    {
      "name": "Charles Matthau"
    },
    {
      "name": "Hoyt Axton",
      "image": "http://image.tmdb.org/t/p/w185/sIJjj88LfVpvnxW56Ffr6qlj7wI.jpg"
    },
    {
      "name": "Paul Bartel",
      "image": "http://image.tmdb.org/t/p/w185/7Kj1Y9V8lfnFXHkjf30H8d3ylQA.jpg"
    }
  ]
}
